rust_tokenizer_pyo3-0.1.0.dist-info/METADATA
rust_tokenizer_pyo3-0.1.0.dist-info/WHEEL
rust_tokenizer_pyo3/__init__.py
rust_tokenizer_pyo3/rust_tokenizer_pyo3.cp311-win_amd64.pyd
rust_tokenizer_pyo3-0.1.0.dist-info/RECORD
